gempaterkini/__init__.py
latestearthquake_id_mp97-0.0.3.dist-info/LICENSE
latestearthquake_id_mp97-0.0.3.dist-info/METADATA
latestearthquake_id_mp97-0.0.3.dist-info/WHEEL
latestearthquake_id_mp97-0.0.3.dist-info/top_level.txt
latestearthquake_id_mp97-0.0.3.dist-info/RECORD
